pytest_portion.py
pytest_portion-0.2.0.dist-info/METADATA
pytest_portion-0.2.0.dist-info/WHEEL
pytest_portion-0.2.0.dist-info/entry_points.txt
pytest_portion-0.2.0.dist-info/licenses/LICENSE
pytest_portion-0.2.0.dist-info/RECORD
